dbmeta/__init__.py
dbmeta/dbmeta.py
dbmeta/settings.py
dbmeta/connections/__init__.py
dbmeta/connections/database.py
dbmeta/connections/exclude.py
dbmeta/connections/postgres.py
dbmeta-0.0.12.dist-info/METADATA
dbmeta-0.0.12.dist-info/WHEEL
dbmeta-0.0.12.dist-info/licenses/LICENSE
dbmeta-0.0.12.dist-info/RECORD
