Metadata-Version: 2.1
Name: dbmeta
Version: 0.0.12
Summary: Inspect database schema, tables and columns and returns a metadata object
Author-email: Francesco Vertemati <verte.fra@gmail.com>
License-File: LICENSE
Classifier: Programming Language :: Python :: 3
Requires-Dist: psycopg>=3.1.4
Provides-Extra: lint
Requires-Dist: black==22.10.0; extra == 'lint'
Requires-Dist: mypy==0.990; extra == 'lint'
Provides-Extra: test
Requires-Dist: psycopg>=3.1.4; extra == 'test'
Requires-Dist: pydantic>=1.10.2; extra == 'test'
Requires-Dist: pytest-cov==4.0.0; extra == 'test'
Requires-Dist: pytest==7.2.0; extra == 'test'
